seavatar.py
seavatar-0.1.1.dist-info/WHEEL
seavatar-0.1.1.dist-info/METADATA
seavatar-0.1.1.dist-info/RECORD
