Metadata-Version: 2.1
Name: seavatar
Version: 0.1.1
Summary: Tool To Generate Beach themed -MLH avatars
Home-page: https://github.com/victorprince/Seavatar
Author: Victor Prince
Author-email: v1kk1x@protonmail.com
